[
  {
    "id": 1,
    "name": "Lugna nätter",
    "price": 1500,
    "isBestseller": true,
    "description": "Vår mest prisvärda ved, ett bra val för den som vill ha bra värde för pengarna. Pris per m³",
    "stock": 4,
    "inventory": 31
  },
  {
    "id": 2,
    "name": "Djupskogsveden",
    "price": 2100,
    "isBestseller": false,
    "description": "En blandning av björk, ek och ask. Perfekt för kalla vinterkvällar och ger en behaglig doft. Pris per m³",
    "stock": 0,
    "inventory": 40
  },
  {
    "id": 3,
    "name": "Björkved Deluxe",
    "price": 2400,
    "isBestseller": false,
    "description": "Björkved av hög kvalitet, väljer du detta kan du inte gå fel. Pris per m³",
    "stock": 14,
    "inventory": 50
  },
  {
    "id": 4,
    "name": "Sommarkväll",
    "price": 2000,
    "isBestseller": true,
    "description": "Perfekt för en sommarkväll vid eldstaden eller eldkorgen. Pris per m³",
    "stock": 0,
    "inventory": 10
  },
  {
    "id": 5,
    "name": "Ask och Björk",
    "price": 2200,
    "isBestseller": false,
    "description": "En blandning av ask och björk, ger en jämn och fin brasa. Pris per m³",
    "stock": 12,
    "inventory": 20
  },
  {
    "id": 6,
    "name": "Premium Ek",
    "price": 2400,
    "isBestseller": true,
    "description": "Vår premium ekved ger mycket värme och har en lång brinntid. Pris per m³",
    "stock": 4,
    "inventory": 15
  }
]